drevixhub/__init__.py
drevixhub/client.py
drevixbot-3.dist-info/METADATA
drevixbot-3.dist-info/WHEEL
drevixbot-3.dist-info/top_level.txt
drevixbot-3.dist-info/RECORD
