Metadata-Version: 2.4
Name: drevixbot
Version: 3
Summary: The official Secure Receiver Gate for Drevix Bots
Author: Drevix Dev
Requires-Dist: requests
Dynamic: author
Dynamic: description
Dynamic: description-content-type
Dynamic: requires-dist
Dynamic: summary
